strangeworks_braket_extension/__init__.py
strangeworks_braket_extension/utils.py
strangeworks_braket_extension/aws/__init__.py
strangeworks_braket_extension/aws/serverless.py
strangeworks_braket_extension/aws/sw_proxy.py
strangeworks_braket_extension/aws/types.py
strangeworks_braket_extension/local_simulator/__init__.py
strangeworks_braket_extension/local_simulator/local.py
strangeworks_braket_extension/local_simulator/plugin.py
strangeworks_braket_extension-0.7.1.dist-info/METADATA
strangeworks_braket_extension-0.7.1.dist-info/WHEEL
strangeworks_braket_extension-0.7.1.dist-info/entry_points.txt
strangeworks_braket_extension-0.7.1.dist-info/RECORD
